testscribe/__init__.py
testscribe/__main__.py
testscribe/api/__init__.py
testscribe/api/alias.py
testscribe/api/io_provider.py
testscribe/api/mock_api.py
testscribe/base_reflection_util.py
testscribe/cli.py
testscribe/code_gen_util.py
testscribe/complex_value_util.py
testscribe/config.py
testscribe/constant.py
testscribe/context.py
testscribe/create_test_cmd.py
testscribe/custom_type.py
testscribe/delete_test_cmd.py
testscribe/description.py
testscribe/error.py
testscribe/eval_expression.py
testscribe/exception_decorator.py
testscribe/execution.py
testscribe/execution_util.py
testscribe/file_info.py
testscribe/gather_referenced_modules.py
testscribe/gen_mock_code.py
testscribe/gen_mock_verification_code.py
testscribe/gen_patch_code.py
testscribe/generate_imports.py
testscribe/generate_tests.py
testscribe/global_var.py
testscribe/ignore.py
testscribe/input_params.py
testscribe/load_scribe_file.py
testscribe/log.py
testscribe/mock_call.py
testscribe/mock_proxy.py
testscribe/mock_proxy_support.py
testscribe/mocking_support.py
testscribe/model.py
testscribe/model_encoder.py
testscribe/model_type.py
testscribe/module.py
testscribe/move_cmd.py
testscribe/namedvalues.py
testscribe/parameter_value_input.py
testscribe/parameter_value_input_cli.py
testscribe/patcher.py
testscribe/reflection_util.py
testscribe/result_assertion.py
testscribe/runtime_values.py
testscribe/save_scribe_file.py
testscribe/scribe_file_key.py
testscribe/special_type.py
testscribe/sync_cmd.py
testscribe/test_name.py
testscribe/transformer.py
testscribe/type_util.py
testscribe/update_test_cmd.py
testscribe/user_triggered_exception.py
testscribe/util.py
testscribe/value_input.py
testscribe/value_input_cli.py
testscribe/value_input_util.py
testscribe/value_util.py
testscribe/yaml_tag.py
testscribe-0.0.3.dist-info/entry_points.txt
testscribe-0.0.3.dist-info/LICENSE.txt
testscribe-0.0.3.dist-info/WHEEL
testscribe-0.0.3.dist-info/METADATA
testscribe-0.0.3.dist-info/RECORD
