Metadata-Version: 2.1
Name: testscribe
Version: 0.0.3
Summary: Unit test automation tool
Home-page: https://github.com/HappyRay/testscribe
License: Apache-2.0
Author: Ray Yang
Author-email: ruiguo@gmail.com
Requires-Python: >=3.7,<4.0
Classifier: License :: OSI Approved :: Apache Software License
Classifier: Programming Language :: Python :: 3
Classifier: Programming Language :: Python :: 3.7
Classifier: Programming Language :: Python :: 3.8
Classifier: Programming Language :: Python :: 3.9
Classifier: Programming Language :: Python :: 3.10
Classifier: Programming Language :: Python :: 3.11
Requires-Dist: PyYAML (>=5.2)
Requires-Dist: typer
Project-URL: Documentation, https://www.pyscribe.org/
Project-URL: Repository, https://github.com/HappyRay/testscribe
